tacacs_plus/__init__.py
tacacs_plus/accounting.py
tacacs_plus/authentication.py
tacacs_plus/authorization.py
tacacs_plus/client.py
tacacs_plus/flags.py
tacacs_plus/packet.py
tacacs_plus-2.6.data/scripts/tacacs_client
tacacs_plus-2.6.dist-info/METADATA
tacacs_plus-2.6.dist-info/RECORD
tacacs_plus-2.6.dist-info/WHEEL
tacacs_plus-2.6.dist-info/top_level.txt
tests/__init__.py
tests/test_tacacs_plus.py
